LICENSE.txt
MANIFEST.in
README.md
app.py
config.py
manage.py
models.py
setup.py
api_1_0/__init__.py
api_1_0/operations/__init__.py
api_1_0/operations/bank.py
cashMake.egg-info/PKG-INFO
cashMake.egg-info/SOURCES.txt
cashMake.egg-info/dependency_links.txt
cashMake.egg-info/not-zip-safe
cashMake.egg-info/top_level.txt
lib/__init__.py
lib/utils.py
lib/operations/__init__.py
lib/operations/bank.py
main/__init__.py
main/view.py