Metadata-Version: 1.0
Name: cashMake
Version: 0.1
Summary: Manage configuration files
Home-page: https://www.baidu.com
Author: Zrush Zhang
Author-email: mrzhzr2004@sina.com
License: GPL
Platform: UNKNOWN
